musicaiz/__init__.py
musicaiz/eval.py
musicaiz/loaders.py
musicaiz/utils.py
musicaiz/version.py
musicaiz/wrappers.py
musicaiz/algorithms/__init__.py
musicaiz/algorithms/harmonic_shift.py
musicaiz/converters/__init__.py
musicaiz/converters/musa_json.py
musicaiz/converters/pretty_midi_musa.py
musicaiz/datasets/__init__.py
musicaiz/datasets/configs.py
musicaiz/datasets/jsbchorales.py
musicaiz/datasets/lmd.py
musicaiz/datasets/maestro.py
musicaiz/datasets/utils.py
musicaiz/features/__init__.py
musicaiz/features/harmony.py
musicaiz/features/pitch.py
musicaiz/features/predict_midi.py
musicaiz/features/rhythm.py
musicaiz/features/self_similarity.py
musicaiz/harmony/__init__.py
musicaiz/harmony/chords.py
musicaiz/harmony/intervals.py
musicaiz/harmony/keys.py
musicaiz/models/__init__.py
musicaiz/models/transformer_composers/__init__.py
musicaiz/models/transformer_composers/configs.py
musicaiz/models/transformer_composers/dataset.py
musicaiz/models/transformer_composers/generate.py
musicaiz/models/transformer_composers/train.py
musicaiz/models/transformer_composers/transformers/__init__.py
musicaiz/models/transformer_composers/transformers/attention.py
musicaiz/models/transformer_composers/transformers/gpt.py
musicaiz/models/transformer_composers/transformers/layers.py
musicaiz/plotters/__init__.py
musicaiz/plotters/pianorolls.py
musicaiz/rhythm/__init__.py
musicaiz/rhythm/quantizer.py
musicaiz/rhythm/timing.py
musicaiz/structure/__init__.py
musicaiz/structure/bars.py
musicaiz/structure/instruments.py
musicaiz/structure/notes.py
musicaiz/tokenizers/__init__.py
musicaiz/tokenizers/encoder.py
musicaiz/tokenizers/mmm.py
musicaiz/tokenizers/one_hot.py
tests/__init__.py
tests/conftest.py
tests/unit/__init__.py
tests/unit/musicaiz/__init__.py
tests/unit/musicaiz/features/__init__.py
tests/unit/musicaiz/features/test_harmony.py
tests/unit/musicaiz/features/test_pitch.py
tests/unit/musicaiz/features/test_rhythm.py
tests/unit/musicaiz/harmony/__init__.py
musicaiz-0.0.2.dist-info/LICENSE.md
musicaiz-0.0.2.dist-info/METADATA
musicaiz-0.0.2.dist-info/WHEEL
musicaiz-0.0.2.dist-info/top_level.txt
musicaiz-0.0.2.dist-info/RECORD
