Metadata-Version: 2.1
Name: musicaiz
Version: 0.0.2
Summary: A python framework for symbolic music generation, evaluation and analysis
Home-page: https://carlosholivan.github.io/musicaiz
Author: Carlos Hernandez-Olivan
Author-email: carlosher@unizar.es
License: ISC
Project-URL: Documentation, https://carlosholivan.github.io/musicaiz/docs
Project-URL: Download, https://github.com/carlosholivan/musicaiz/releases
Project-URL: Source, https://github.com/carlosholivan/musicaiz
Project-URL: Tracker, https://github.com/carlosholivan/musicaiz/issues
Classifier: License :: OSI Approved :: GNU Affero General Public License v3
Classifier: Programming Language :: Python
Classifier: Development Status :: 3 - Alpha
Classifier: Intended Audience :: Developers
Classifier: Topic :: Multimedia :: Sound/Audio :: Analysis
Classifier: Framework :: Matplotlib
Classifier: Programming Language :: Python :: 3
Classifier: Programming Language :: Python :: 3.6
Classifier: Programming Language :: Python :: 3.7
Classifier: Programming Language :: Python :: 3.8
Classifier: Programming Language :: Python :: 3.9
Requires-Python: >=3.6
License-File: LICENSE.md
Requires-Dist: pretty-midi (==0.2.9)
Requires-Dist: pytest (==6.2.4)
Requires-Dist: matplotlib (==3.4.3)
Requires-Dist: plotly (==5.8.0)
Requires-Dist: mypy (==0.960)
Requires-Dist: seaborn (==0.11.2)
Requires-Dist: pre-commit (==2.19.0)
Requires-Dist: tqdm (==4.64.0)
Requires-Dist: networkx (==2.8.3)
Requires-Dist: sklearn (==0.0)
Requires-Dist: gradio (==3.0.15)
Requires-Dist: torchsummary (==1.5.1)
Requires-Dist: prettytable (==3.3.0)
Requires-Dist: torch (==1.11.0)
Provides-Extra: display
Requires-Dist: matplotlib (>=3.3.0) ; extra == 'display'
Provides-Extra: docs
Requires-Dist: sphinx-rtd-theme (==0.5.*) ; extra == 'docs'
Requires-Dist: sphinx-design (==0.1.0) ; extra == 'docs'
Requires-Dist: sphinx-panels (==0.6.0) ; extra == 'docs'
Requires-Dist: nbsphinx (==0.8.8) ; extra == 'docs'
Requires-Dist: sphinx (!=1.3.1) ; extra == 'docs'
Requires-Dist: numpydoc (==1.1.0) ; extra == 'docs'
Requires-Dist: matplotlib (>=3.3.0) ; extra == 'docs'
Requires-Dist: sphinx-multiversion (>=0.2.3) ; extra == 'docs'
Requires-Dist: sphinx-gallery (>=0.7) ; extra == 'docs'
Requires-Dist: ipython (>=7.0) ; extra == 'docs'
Requires-Dist: sphinxcontrib-svg2pdfconverter ; extra == 'docs'
Requires-Dist: presets ; extra == 'docs'
Requires-Dist: sphinx-book-theme (==0.3.2) ; extra == 'docs'
Provides-Extra: tests
Requires-Dist: pytest-mpl ; extra == 'tests'
Requires-Dist: pytest-cov ; extra == 'tests'
Requires-Dist: pytest ; extra == 'tests'
